langsets/__init__.py
langsets/documents/__init__.py
langsets-0.1.0.dist-info/METADATA
langsets-0.1.0.dist-info/WHEEL
langsets-0.1.0.dist-info/top_level.txt
langsets-0.1.0.dist-info/RECORD
