Metadata-Version: 2.4
Name: langsets
Version: 0.1.0
Summary: Add your description here
Requires-Python: >=3.13
Requires-Dist: pydantic-ai>=1.0.10
